[{"name":"client_config","qualifiedName":"client_config","href":"client_config/client_config-library.html","type":"library","overriddenDepth":0,"packageName":"fluent_aliyun_oss"},{"name":"AliyunOssClientConfig","qualifiedName":"client_config.AliyunOssClientConfig","href":"client_config/AliyunOssClientConfig-class.html","type":"class","overriddenDepth":0,"packageName":"fluent_aliyun_oss","enclosedBy":{"name":"client_config","type":"library"}},{"name":"AliyunOssClientConfig","qualifiedName":"client_config.AliyunOssClientConfig.AliyunOssClientConfig","href":"client_config/AliyunOssClientConfig/AliyunOssClientConfig.html","type":"constructor","overriddenDepth":0,"packageName":"fluent_aliyun_oss","enclosedBy":{"name":"AliyunOssClientConfig","type":"class"}},{"name":"accessKeyId","qualifiedName":"client_config.AliyunOssClientConfig.accessKeyId","href":"client_config/AliyunOssClientConfig/accessKeyId.html","type":"property","overriddenDepth":0,"packageName":"fluent_aliyun_oss","enclosedBy":{"name":"AliyunOssClientConfig","type":"class"}},{"name":"accessKeySecret","qualifiedName":"client_config.AliyunOssClientConfig.accessKeySecret","href":"client_config/AliyunOssClientConfig/accessKeySecret.html","type":"property","overriddenDepth":0,"packageName":"fluent_aliyun_oss","enclosedBy":{"name":"AliyunOssClientConfig","type":"class"}},{"name":"endpoint","qualifiedName":"client_config.AliyunOssClientConfig.endpoint","href":"client_config/AliyunOssClientConfig/endpoint.html","type":"property","overriddenDepth":0,"packageName":"fluent_aliyun_oss","enclosedBy":{"name":"AliyunOssClientConfig","type":"class"}},{"name":"securityToken","qualifiedName":"client_config.AliyunOssClientConfig.securityToken","href":"client_config/AliyunOssClientConfig/securityToken.html","type":"property","overriddenDepth":0,"packageName":"fluent_aliyun_oss","enclosedBy":{"name":"AliyunOssClientConfig","type":"class"}},{"name":"toMap","qualifiedName":"client_config.AliyunOssClientConfig.toMap","href":"client_config/AliyunOssClientConfig/toMap.html","type":"method","overriddenDepth":0,"packageName":"fluent_aliyun_oss","enclosedBy":{"name":"AliyunOssClientConfig","type":"class"}},{"name":"fluent_aliyun_oss","qualifiedName":"fluent_aliyun_oss","href":"fluent_aliyun_oss/fluent_aliyun_oss-library.html","type":"library","overriddenDepth":0,"packageName":"fluent_aliyun_oss"},{"name":"CLIENT_KEY","qualifiedName":"fluent_aliyun_oss.CLIENT_KEY","href":"fluent_aliyun_oss/CLIENT_KEY-constant.html","type":"top-level constant","overriddenDepth":0,"packageName":"fluent_aliyun_oss","enclosedBy":{"name":"fluent_aliyun_oss","type":"library"}},{"name":"FluentAliyunOss","qualifiedName":"fluent_aliyun_oss.FluentAliyunOss","href":"fluent_aliyun_oss/FluentAliyunOss-class.html","type":"class","overriddenDepth":0,"packageName":"fluent_aliyun_oss","enclosedBy":{"name":"fluent_aliyun_oss","type":"library"}},{"name":"FluentAliyunOss","qualifiedName":"fluent_aliyun_oss.FluentAliyunOss.FluentAliyunOss","href":"fluent_aliyun_oss/FluentAliyunOss/FluentAliyunOss.html","type":"constructor","overriddenDepth":0,"packageName":"fluent_aliyun_oss","enclosedBy":{"name":"FluentAliyunOss","type":"class"}},{"name":"dispose","qualifiedName":"fluent_aliyun_oss.FluentAliyunOss.dispose","href":"fluent_aliyun_oss/FluentAliyunOss/dispose.html","type":"method","overriddenDepth":0,"packageName":"fluent_aliyun_oss","enclosedBy":{"name":"FluentAliyunOss","type":"class"}},{"name":"init","qualifiedName":"fluent_aliyun_oss.FluentAliyunOss.init","href":"fluent_aliyun_oss/FluentAliyunOss/init.html","type":"method","overriddenDepth":0,"packageName":"fluent_aliyun_oss","enclosedBy":{"name":"FluentAliyunOss","type":"class"}},{"name":"platformVersion","qualifiedName":"fluent_aliyun_oss.FluentAliyunOss.platformVersion","href":"fluent_aliyun_oss/FluentAliyunOss/platformVersion.html","type":"property","overriddenDepth":0,"packageName":"fluent_aliyun_oss","enclosedBy":{"name":"FluentAliyunOss","type":"class"}},{"name":"putObject","qualifiedName":"fluent_aliyun_oss.FluentAliyunOss.putObject","href":"fluent_aliyun_oss/FluentAliyunOss/putObject.html","type":"method","overriddenDepth":0,"packageName":"fluent_aliyun_oss","enclosedBy":{"name":"FluentAliyunOss","type":"class"}},{"name":"signUrl","qualifiedName":"fluent_aliyun_oss.FluentAliyunOss.signUrl","href":"fluent_aliyun_oss/FluentAliyunOss/signUrl.html","type":"method","overriddenDepth":0,"packageName":"fluent_aliyun_oss","enclosedBy":{"name":"FluentAliyunOss","type":"class"}},{"name":"oss_credential","qualifiedName":"oss_credential","href":"oss_credential/oss_credential-library.html","type":"library","overriddenDepth":0,"packageName":"fluent_aliyun_oss"},{"name":"OSSCredential","qualifiedName":"oss_credential.OSSCredential","href":"oss_credential/OSSCredential-class.html","type":"class","overriddenDepth":0,"packageName":"fluent_aliyun_oss","enclosedBy":{"name":"oss_credential","type":"library"}},{"name":"OSSCredential","qualifiedName":"oss_credential.OSSCredential.OSSCredential","href":"oss_credential/OSSCredential/OSSCredential.html","type":"constructor","overriddenDepth":0,"packageName":"fluent_aliyun_oss","enclosedBy":{"name":"OSSCredential","type":"class"}},{"name":"accessKeyId","qualifiedName":"oss_credential.OSSCredential.accessKeyId","href":"oss_credential/OSSCredential/accessKeyId.html","type":"property","overriddenDepth":0,"packageName":"fluent_aliyun_oss","enclosedBy":{"name":"OSSCredential","type":"class"}},{"name":"accessKeySecret","qualifiedName":"oss_credential.OSSCredential.accessKeySecret","href":"oss_credential/OSSCredential/accessKeySecret.html","type":"property","overriddenDepth":0,"packageName":"fluent_aliyun_oss","enclosedBy":{"name":"OSSCredential","type":"class"}},{"name":"expiration","qualifiedName":"oss_credential.OSSCredential.expiration","href":"oss_credential/OSSCredential/expiration.html","type":"property","overriddenDepth":0,"packageName":"fluent_aliyun_oss","enclosedBy":{"name":"OSSCredential","type":"class"}},{"name":"securityToken","qualifiedName":"oss_credential.OSSCredential.securityToken","href":"oss_credential/OSSCredential/securityToken.html","type":"property","overriddenDepth":0,"packageName":"fluent_aliyun_oss","enclosedBy":{"name":"OSSCredential","type":"class"}},{"name":"put_object_event_handler","qualifiedName":"put_object_event_handler","href":"put_object_event_handler/put_object_event_handler-library.html","type":"library","overriddenDepth":0,"packageName":"fluent_aliyun_oss"},{"name":"OnProgress","qualifiedName":"put_object_event_handler.OnProgress","href":"put_object_event_handler/OnProgress.html","type":"typedef","overriddenDepth":0,"packageName":"fluent_aliyun_oss","enclosedBy":{"name":"put_object_event_handler","type":"library"}},{"name":"OnUploadFailure","qualifiedName":"put_object_event_handler.OnUploadFailure","href":"put_object_event_handler/OnUploadFailure.html","type":"typedef","overriddenDepth":0,"packageName":"fluent_aliyun_oss","enclosedBy":{"name":"put_object_event_handler","type":"library"}},{"name":"OnUploadSuccess","qualifiedName":"put_object_event_handler.OnUploadSuccess","href":"put_object_event_handler/OnUploadSuccess.html","type":"typedef","overriddenDepth":0,"packageName":"fluent_aliyun_oss","enclosedBy":{"name":"put_object_event_handler","type":"library"}},{"name":"PutObjectEventHandler","qualifiedName":"put_object_event_handler.PutObjectEventHandler","href":"put_object_event_handler/PutObjectEventHandler-class.html","type":"class","overriddenDepth":0,"packageName":"fluent_aliyun_oss","enclosedBy":{"name":"put_object_event_handler","type":"library"}},{"name":"PutObjectEventHandler","qualifiedName":"put_object_event_handler.PutObjectEventHandler.PutObjectEventHandler","href":"put_object_event_handler/PutObjectEventHandler/PutObjectEventHandler.html","type":"constructor","overriddenDepth":0,"packageName":"fluent_aliyun_oss","enclosedBy":{"name":"PutObjectEventHandler","type":"class"}},{"name":"dispatch","qualifiedName":"put_object_event_handler.PutObjectEventHandler.dispatch","href":"put_object_event_handler/PutObjectEventHandler/dispatch.html","type":"method","overriddenDepth":0,"packageName":"fluent_aliyun_oss","enclosedBy":{"name":"PutObjectEventHandler","type":"class"}},{"name":"onFailure","qualifiedName":"put_object_event_handler.PutObjectEventHandler.onFailure","href":"put_object_event_handler/PutObjectEventHandler/onFailure.html","type":"property","overriddenDepth":0,"packageName":"fluent_aliyun_oss","enclosedBy":{"name":"PutObjectEventHandler","type":"class"}},{"name":"onProgress","qualifiedName":"put_object_event_handler.PutObjectEventHandler.onProgress","href":"put_object_event_handler/PutObjectEventHandler/onProgress.html","type":"property","overriddenDepth":0,"packageName":"fluent_aliyun_oss","enclosedBy":{"name":"PutObjectEventHandler","type":"class"}},{"name":"onSuccess","qualifiedName":"put_object_event_handler.PutObjectEventHandler.onSuccess","href":"put_object_event_handler/PutObjectEventHandler/onSuccess.html","type":"property","overriddenDepth":0,"packageName":"fluent_aliyun_oss","enclosedBy":{"name":"PutObjectEventHandler","type":"class"}},{"name":"taskId","qualifiedName":"put_object_event_handler.PutObjectEventHandler.taskId","href":"put_object_event_handler/PutObjectEventHandler/taskId.html","type":"property","overriddenDepth":0,"packageName":"fluent_aliyun_oss","enclosedBy":{"name":"PutObjectEventHandler","type":"class"}},{"name":"put_object_progress","qualifiedName":"put_object_progress","href":"put_object_progress/put_object_progress-library.html","type":"library","overriddenDepth":0,"packageName":"fluent_aliyun_oss"},{"name":"PutObjectProgress","qualifiedName":"put_object_progress.PutObjectProgress","href":"put_object_progress/PutObjectProgress-class.html","type":"class","overriddenDepth":0,"packageName":"fluent_aliyun_oss","enclosedBy":{"name":"put_object_progress","type":"library"}},{"name":"PutObjectProgress","qualifiedName":"put_object_progress.PutObjectProgress.PutObjectProgress","href":"put_object_progress/PutObjectProgress/PutObjectProgress.html","type":"constructor","overriddenDepth":0,"packageName":"fluent_aliyun_oss","enclosedBy":{"name":"PutObjectProgress","type":"class"}},{"name":"currentSize","qualifiedName":"put_object_progress.PutObjectProgress.currentSize","href":"put_object_progress/PutObjectProgress/currentSize.html","type":"property","overriddenDepth":0,"packageName":"fluent_aliyun_oss","enclosedBy":{"name":"PutObjectProgress","type":"class"}},{"name":"progress","qualifiedName":"put_object_progress.PutObjectProgress.progress","href":"put_object_progress/PutObjectProgress/progress.html","type":"property","overriddenDepth":0,"packageName":"fluent_aliyun_oss","enclosedBy":{"name":"PutObjectProgress","type":"class"}},{"name":"totalSize","qualifiedName":"put_object_progress.PutObjectProgress.totalSize","href":"put_object_progress/PutObjectProgress/totalSize.html","type":"property","overriddenDepth":0,"packageName":"fluent_aliyun_oss","enclosedBy":{"name":"PutObjectProgress","type":"class"}},{"name":"put_object_request","qualifiedName":"put_object_request","href":"put_object_request/put_object_request-library.html","type":"library","overriddenDepth":0,"packageName":"fluent_aliyun_oss"},{"name":"AliyunOssPutObjectRequest","qualifiedName":"put_object_request.AliyunOssPutObjectRequest","href":"put_object_request/AliyunOssPutObjectRequest-class.html","type":"class","overriddenDepth":0,"packageName":"fluent_aliyun_oss","enclosedBy":{"name":"put_object_request","type":"library"}},{"name":"AliyunOssPutObjectRequest","qualifiedName":"put_object_request.AliyunOssPutObjectRequest.AliyunOssPutObjectRequest","href":"put_object_request/AliyunOssPutObjectRequest/AliyunOssPutObjectRequest.html","type":"constructor","overriddenDepth":0,"packageName":"fluent_aliyun_oss","enclosedBy":{"name":"AliyunOssPutObjectRequest","type":"class"}},{"name":"bucketName","qualifiedName":"put_object_request.AliyunOssPutObjectRequest.bucketName","href":"put_object_request/AliyunOssPutObjectRequest/bucketName.html","type":"property","overriddenDepth":0,"packageName":"fluent_aliyun_oss","enclosedBy":{"name":"AliyunOssPutObjectRequest","type":"class"}},{"name":"file","qualifiedName":"put_object_request.AliyunOssPutObjectRequest.file","href":"put_object_request/AliyunOssPutObjectRequest/file.html","type":"property","overriddenDepth":0,"packageName":"fluent_aliyun_oss","enclosedBy":{"name":"AliyunOssPutObjectRequest","type":"class"}},{"name":"objectName","qualifiedName":"put_object_request.AliyunOssPutObjectRequest.objectName","href":"put_object_request/AliyunOssPutObjectRequest/objectName.html","type":"property","overriddenDepth":0,"packageName":"fluent_aliyun_oss","enclosedBy":{"name":"AliyunOssPutObjectRequest","type":"class"}},{"name":"toMap","qualifiedName":"put_object_request.AliyunOssPutObjectRequest.toMap","href":"put_object_request/AliyunOssPutObjectRequest/toMap.html","type":"method","overriddenDepth":0,"packageName":"fluent_aliyun_oss","enclosedBy":{"name":"AliyunOssPutObjectRequest","type":"class"}},{"name":"put_object_response","qualifiedName":"put_object_response","href":"put_object_response/put_object_response-library.html","type":"library","overriddenDepth":0,"packageName":"fluent_aliyun_oss"},{"name":"PutObjectResponse","qualifiedName":"put_object_response.PutObjectResponse","href":"put_object_response/PutObjectResponse-class.html","type":"class","overriddenDepth":0,"packageName":"fluent_aliyun_oss","enclosedBy":{"name":"put_object_response","type":"library"}},{"name":"PutObjectResponse","qualifiedName":"put_object_response.PutObjectResponse.PutObjectResponse","href":"put_object_response/PutObjectResponse/PutObjectResponse.html","type":"constructor","overriddenDepth":0,"packageName":"fluent_aliyun_oss","enclosedBy":{"name":"PutObjectResponse","type":"class"}},{"name":"progress","qualifiedName":"put_object_response.PutObjectResponse.progress","href":"put_object_response/PutObjectResponse/progress.html","type":"property","overriddenDepth":0,"packageName":"fluent_aliyun_oss","enclosedBy":{"name":"PutObjectResponse","type":"class"}},{"name":"result","qualifiedName":"put_object_response.PutObjectResponse.result","href":"put_object_response/PutObjectResponse/result.html","type":"property","overriddenDepth":0,"packageName":"fluent_aliyun_oss","enclosedBy":{"name":"PutObjectResponse","type":"class"}},{"name":"put_object_result","qualifiedName":"put_object_result","href":"put_object_result/put_object_result-library.html","type":"library","overriddenDepth":0,"packageName":"fluent_aliyun_oss"},{"name":"PutObjectResult","qualifiedName":"put_object_result.PutObjectResult","href":"put_object_result/PutObjectResult-class.html","type":"class","overriddenDepth":0,"packageName":"fluent_aliyun_oss","enclosedBy":{"name":"put_object_result","type":"library"}},{"name":"PutObjectResult","qualifiedName":"put_object_result.PutObjectResult.PutObjectResult","href":"put_object_result/PutObjectResult/PutObjectResult.html","type":"constructor","overriddenDepth":0,"packageName":"fluent_aliyun_oss","enclosedBy":{"name":"PutObjectResult","type":"class"}},{"name":"currentSize","qualifiedName":"put_object_result.PutObjectResult.currentSize","href":"put_object_result/PutObjectResult/currentSize.html","type":"property","overriddenDepth":0,"packageName":"fluent_aliyun_oss","enclosedBy":{"name":"PutObjectResult","type":"class"}},{"name":"errorMessage","qualifiedName":"put_object_result.PutObjectResult.errorMessage","href":"put_object_result/PutObjectResult/errorMessage.html","type":"property","overriddenDepth":0,"packageName":"fluent_aliyun_oss","enclosedBy":{"name":"PutObjectResult","type":"class"}},{"name":"isError","qualifiedName":"put_object_result.PutObjectResult.isError","href":"put_object_result/PutObjectResult/isError.html","type":"property","overriddenDepth":0,"packageName":"fluent_aliyun_oss","enclosedBy":{"name":"PutObjectResult","type":"class"}},{"name":"isFinished","qualifiedName":"put_object_result.PutObjectResult.isFinished","href":"put_object_result/PutObjectResult/isFinished.html","type":"property","overriddenDepth":0,"packageName":"fluent_aliyun_oss","enclosedBy":{"name":"PutObjectResult","type":"class"}},{"name":"taskId","qualifiedName":"put_object_result.PutObjectResult.taskId","href":"put_object_result/PutObjectResult/taskId.html","type":"property","overriddenDepth":0,"packageName":"fluent_aliyun_oss","enclosedBy":{"name":"PutObjectResult","type":"class"}},{"name":"toString","qualifiedName":"put_object_result.PutObjectResult.toString","href":"put_object_result/PutObjectResult/toString.html","type":"method","overriddenDepth":1,"packageName":"fluent_aliyun_oss","enclosedBy":{"name":"PutObjectResult","type":"class"}},{"name":"totalSize","qualifiedName":"put_object_result.PutObjectResult.totalSize","href":"put_object_result/PutObjectResult/totalSize.html","type":"property","overriddenDepth":0,"packageName":"fluent_aliyun_oss","enclosedBy":{"name":"PutObjectResult","type":"class"}},{"name":"url","qualifiedName":"put_object_result.PutObjectResult.url","href":"put_object_result/PutObjectResult/url.html","type":"property","overriddenDepth":0,"packageName":"fluent_aliyun_oss","enclosedBy":{"name":"PutObjectResult","type":"class"}}]
